odoo/addons/l10n_it_rea/README.rst
odoo/addons/l10n_it_rea/__init__.py
odoo/addons/l10n_it_rea/__manifest__.py
odoo/addons/l10n_it_rea/i18n/am.po
odoo/addons/l10n_it_rea/i18n/ar.po
odoo/addons/l10n_it_rea/i18n/bg.po
odoo/addons/l10n_it_rea/i18n/bs.po
odoo/addons/l10n_it_rea/i18n/ca.po
odoo/addons/l10n_it_rea/i18n/cs.po
odoo/addons/l10n_it_rea/i18n/da.po
odoo/addons/l10n_it_rea/i18n/de.po
odoo/addons/l10n_it_rea/i18n/el_GR.po
odoo/addons/l10n_it_rea/i18n/en_GB.po
odoo/addons/l10n_it_rea/i18n/es.po
odoo/addons/l10n_it_rea/i18n/es_AR.po
odoo/addons/l10n_it_rea/i18n/es_CR.po
odoo/addons/l10n_it_rea/i18n/es_EC.po
odoo/addons/l10n_it_rea/i18n/es_MX.po
odoo/addons/l10n_it_rea/i18n/es_VE.po
odoo/addons/l10n_it_rea/i18n/et.po
odoo/addons/l10n_it_rea/i18n/fi.po
odoo/addons/l10n_it_rea/i18n/fr.po
odoo/addons/l10n_it_rea/i18n/fr_CA.po
odoo/addons/l10n_it_rea/i18n/fr_CH.po
odoo/addons/l10n_it_rea/i18n/gl.po
odoo/addons/l10n_it_rea/i18n/hr.po
odoo/addons/l10n_it_rea/i18n/hr_HR.po
odoo/addons/l10n_it_rea/i18n/hu.po
odoo/addons/l10n_it_rea/i18n/it.po
odoo/addons/l10n_it_rea/i18n/ja.po
odoo/addons/l10n_it_rea/i18n/l10n_it_rea.pot
odoo/addons/l10n_it_rea/i18n/lt.po
odoo/addons/l10n_it_rea/i18n/lv.po
odoo/addons/l10n_it_rea/i18n/mk.po
odoo/addons/l10n_it_rea/i18n/mn.po
odoo/addons/l10n_it_rea/i18n/nb.po
odoo/addons/l10n_it_rea/i18n/nb_NO.po
odoo/addons/l10n_it_rea/i18n/nl.po
odoo/addons/l10n_it_rea/i18n/nl_BE.po
odoo/addons/l10n_it_rea/i18n/pl.po
odoo/addons/l10n_it_rea/i18n/pt.po
odoo/addons/l10n_it_rea/i18n/pt_BR.po
odoo/addons/l10n_it_rea/i18n/pt_PT.po
odoo/addons/l10n_it_rea/i18n/ro.po
odoo/addons/l10n_it_rea/i18n/ru.po
odoo/addons/l10n_it_rea/i18n/sl.po
odoo/addons/l10n_it_rea/i18n/sr@latin.po
odoo/addons/l10n_it_rea/i18n/sv.po
odoo/addons/l10n_it_rea/i18n/th.po
odoo/addons/l10n_it_rea/i18n/tr.po
odoo/addons/l10n_it_rea/i18n/vi.po
odoo/addons/l10n_it_rea/i18n/zh_CN.po
odoo/addons/l10n_it_rea/i18n/zh_TW.po
odoo/addons/l10n_it_rea/models/__init__.py
odoo12_addon_l10n_it_rea-12.0.1.0.4.dist-info/METADATA
odoo12_addon_l10n_it_rea-12.0.1.0.4.dist-info/WHEEL
odoo12_addon_l10n_it_rea-12.0.1.0.4.dist-info/top_level.txt
odoo12_addon_l10n_it_rea-12.0.1.0.4.dist-info/RECORD
